conannio/__init__.py
conannio/build.py
conannio/nioconanfile.py
conannio/simulate.py
niobuild-20230204.dist-info/METADATA
niobuild-20230204.dist-info/WHEEL
niobuild-20230204.dist-info/entry_points.txt
niobuild-20230204.dist-info/top_level.txt
niobuild-20230204.dist-info/RECORD
