Metadata-Version: 2.1
Name: niobuild
Version: 20230204
Requires-Dist: conan (==1.58.0)
